pysecuritas/__init__.py
pysecuritas/__version__.py
pysecuritas/api/__init__.py
pysecuritas/api/alarm.py
pysecuritas/api/camera.py
pysecuritas/api/installation.py
pysecuritas/cli/__init__.py
pysecuritas/cli/cli_command.py
pysecuritas/core/__init__.py
pysecuritas/core/session.py
pysecuritas/core/utils.py
pysecuritas-0.1.6.dist-info/LICENSE
pysecuritas-0.1.6.dist-info/METADATA
pysecuritas-0.1.6.dist-info/WHEEL
pysecuritas-0.1.6.dist-info/entry_points.txt
pysecuritas-0.1.6.dist-info/top_level.txt
pysecuritas-0.1.6.dist-info/RECORD
