Metadata-Version: 2.1
Name: pysecuritas
Version: 0.1.6
Summary: Python library to retrieve and interact with securitas devices.
Home-page: https://github.com/Cebeerre/pysecuritas
Author: 
Author-email: 
License: MIT License
Project-URL: Source, https://github.com/Cebeerre/pysecuritas
Project-URL: Tracker, https://github.com/Cebeerre/pysecuritas/issues
Platform: UNKNOWN
Classifier: License :: OSI Approved :: MIT License
Classifier: Intended Audience :: Developers
Classifier: Natural Language :: English
Classifier: Operating System :: OS Independent
Classifier: Programming Language :: Python
Classifier: Programming Language :: Python :: 2
Classifier: Programming Language :: Python :: 2.7
Classifier: Programming Language :: Python :: 3
Classifier: Programming Language :: Python :: 3.5
Classifier: Programming Language :: Python :: 3.6
Classifier: Programming Language :: Python :: 3.7
Classifier: Programming Language :: Python :: 3.8
Classifier: Programming Language :: Python :: 3.9
Requires-Python: >=2.7, !=3.0.*, !=3.1.*, !=3.2.*, !=3.3.*, !=3.4.*
Requires-Dist: xmltodict (>=0.12.0)
Requires-Dist: requests (>=2.25.0)
